PyDNI/__init__.py
PyDNI/birthdates.py
PyDNI/cif.py
PyDNI/dni.py
PyDNI/emails.py
PyDNI/faker_provider.py
PyDNI/generator.py
PyDNI/nie.py
PyDNI/nif.py
PyDNI/phone.py
PyDNI/utils.py
pydni-0.9.0.dist-info/licenses/LICENSE
pydni-0.9.0.dist-info/METADATA
pydni-0.9.0.dist-info/WHEEL
pydni-0.9.0.dist-info/top_level.txt
pydni-0.9.0.dist-info/RECORD
